tracethat/__init__.py
tracethat/crypto.py
tracethat/json_marhsaller.py
tracethat/json_marshaller_test.py
tracethat/log_test.py
tracethat/runtime_config.py
tracethat/tracethat_async_test.py
tracethat/tracethat_impl.py
tracethat/tracethat_test.py
tracethat/ws_reporter.py
tracethat-1.1.0.dist-info/LICENSE
tracethat-1.1.0.dist-info/METADATA
tracethat-1.1.0.dist-info/WHEEL
tracethat-1.1.0.dist-info/top_level.txt
tracethat-1.1.0.dist-info/RECORD
