Metadata-Version: 2.1
Name: tracethat
Version: 1.1.0
Summary: tracethat.dev reporter for Python
Author-email: Kacper Pietrzak <kacpietrzak@gmail.com>
License: The MIT License (MIT) Copyright (c) 2024 Kacper Pietrzak
Project-URL: Homepage, https://tracethat.dev
Project-URL: Repository, https://github.com/yourusername/tracethat
Keywords: tracing,logging,debugging
Classifier: Programming Language :: Python :: 3
Classifier: License :: OSI Approved :: MIT License
Classifier: Operating System :: OS Independent
Requires-Python: >=3.6
License-File: LICENSE
Requires-Dist: typing_extensions>=4.12.2
Requires-Dist: cryptography>=42.0.3
Requires-Dist: aiohttp>=3.9.5
